ffmcp/__init__.py
ffmcp/brain.py
ffmcp/cli.py
ffmcp/config.py
ffmcp/agents/__init__.py
ffmcp/agents/actions.py
ffmcp/agents/agent.py
ffmcp/agents/team.py
ffmcp/providers/__init__.py
ffmcp/providers/ai33_provider.py
ffmcp/providers/aimlapi_provider.py
ffmcp/providers/anthropic_provider.py
ffmcp/providers/base.py
ffmcp/providers/cohere_provider.py
ffmcp/providers/deepseek_provider.py
ffmcp/providers/gemini_provider.py
ffmcp/providers/groq_provider.py
ffmcp/providers/mistral_provider.py
ffmcp/providers/openai_provider.py
ffmcp/providers/perplexity_provider.py
ffmcp/providers/together_provider.py
ffmcp/voiceover/__init__.py
ffmcp/voiceover/base.py
ffmcp/voiceover/elevenlabs_provider.py
ffmcp/voiceover/fishaudio_provider.py
ffmcp-0.1.10.dist-info/METADATA
ffmcp-0.1.10.dist-info/WHEEL
ffmcp-0.1.10.dist-info/entry_points.txt
ffmcp-0.1.10.dist-info/top_level.txt
ffmcp-0.1.10.dist-info/RECORD
